sftpclone/__init__.py
sftpclone/sftpclone.py
sftpclone/t/__init__.py
sftpclone/t/stub_sftp.py
sftpclone/t/test_sftpclone.py
sftpclone/t/utils.py
sftpclone-1.2.2.data/scripts/sftpclone
sftpclone-1.2.2.dist-info/METADATA
sftpclone-1.2.2.dist-info/RECORD
sftpclone-1.2.2.dist-info/WHEEL
sftpclone-1.2.2.dist-info/top_level.txt
