Metadata-Version: 2.1
Name: sftpclone
Version: 1.2.2
Summary: A tool for cloning/syncing a local directory tree with an SFTP server.
Home-page: https://github.com/unbit/sftpclone
Author: Adriano Di Luzio
Author-email: adrianodl@hotmail.it
License: MIT
Keywords: sftpclone,sftp,sync,ftp,ssh
Platform: UNKNOWN
Classifier: Programming Language :: Python
Classifier: Programming Language :: Python :: 2
Classifier: Programming Language :: Python :: 2.7
Classifier: Programming Language :: Python :: 3
Classifier: Programming Language :: Python :: 3.4
Classifier: Programming Language :: Python :: 3.5
Classifier: Programming Language :: Python :: 3.6
Classifier: Programming Language :: Python :: 3.7
Classifier: Development Status :: 6 - Mature
Classifier: Environment :: Other Environment
Classifier: Intended Audience :: Developers
Classifier: Intended Audience :: End Users/Desktop
Classifier: Intended Audience :: Information Technology
Classifier: License :: OSI Approved :: MIT License
Classifier: Operating System :: OS Independent
Classifier: Topic :: System :: Archiving :: Backup
Classifier: Topic :: System :: Archiving :: Mirroring
Classifier: Topic :: Internet :: File Transfer Protocol (FTP)
Classifier: Topic :: Utilities
Requires-Dist: paramiko (==2.4.1)
